AIS/__init__.py
AIS/ais.py
AIS/exceptions.py
AIS/pdf.py
AIS/py.typed
AIS/types.py
AIS2.py-2.3.0.dist-info/AUTHORS.rst
AIS2.py-2.3.0.dist-info/LICENSE
AIS2.py-2.3.0.dist-info/METADATA
AIS2.py-2.3.0.dist-info/WHEEL
AIS2.py-2.3.0.dist-info/top_level.txt
AIS2.py-2.3.0.dist-info/RECORD
