Metadata-Version: 2.1
Name: AIS2.py
Version: 2.3.0
Summary: Python interface for the Swisscom All-in Signing Service
Home-page: https://pypi.python.org/pypi/AIS2.py
Author: Camptocamp
Author-email: info@camptocamp.com
Maintainer: Seantis GmbH
Maintainer-email: info@seantis.ch
License: GNU Affero General Public License v3 or later (AGPLv3+)
Project-URL: Bug Tracker, https://pypi.python.org/pypi/AIS2.py/issues
Classifier: Development Status :: 4 - Beta
Classifier: License :: OSI Approved
Classifier: License :: OSI Approved :: GNU Affero General Public License v3 or later (AGPLv3+)
Classifier: Programming Language :: Python
Classifier: Programming Language :: Python :: 3
Classifier: Programming Language :: Python :: 3.8
Classifier: Programming Language :: Python :: 3.9
Classifier: Programming Language :: Python :: 3.10
Classifier: Programming Language :: Python :: 3.11
Classifier: Programming Language :: Python :: 3.12
Classifier: Programming Language :: Python :: 3.13
Classifier: Programming Language :: Python :: Implementation :: CPython
Classifier: Programming Language :: Python :: Implementation :: PyPy
Requires-Python: >=3.8
License-File: LICENSE
License-File: AUTHORS.rst
Requires-Dist: requests>=2.0
Requires-Dist: pyHanko>=0.9.0
